PBmaths/__init__.py
PBmaths/prak_basic_maths.py
PBmaths-0.1.dist-info/METADATA
PBmaths-0.1.dist-info/WHEEL
PBmaths-0.1.dist-info/top_level.txt
PBmaths-0.1.dist-info/RECORD
